html_table_extractor/__init__.py
html_table_extractor/extractor.py
isaacto_html_table_extractor-1.4.0.1.dist-info/LICENSE
isaacto_html_table_extractor-1.4.0.1.dist-info/METADATA
isaacto_html_table_extractor-1.4.0.1.dist-info/WHEEL
isaacto_html_table_extractor-1.4.0.1.dist-info/top_level.txt
isaacto_html_table_extractor-1.4.0.1.dist-info/RECORD
