Metadata-Version: 2.1
Name: isaacto-html-table-extractor
Version: 1.4.0.1
Summary: A python library for extracting data from html table
Home-page: https://github.com/isaacto/html-table-extractor
Author: Isaac To
Author-email: isaac.to@gmail.com
License: MIT
Keywords: html table beautifulsoup crawler scrape
Platform: UNKNOWN
Classifier: Development Status :: 3 - Alpha
Classifier: Intended Audience :: Developers
Classifier: License :: OSI Approved :: MIT License
Classifier: Programming Language :: Python :: 2
Classifier: Programming Language :: Python :: 2.7
Classifier: Programming Language :: Python :: 3
Classifier: Programming Language :: Python :: 3.5
Requires-Dist: beautifulsoup4 (>=4.0.0)
